topsis_Akshat_102203644/__init__.py
topsis_Akshat_102203644/topsis.py
topsis_akshat_102203644-1.2.5.dist-info/METADATA
topsis_akshat_102203644-1.2.5.dist-info/WHEEL
topsis_akshat_102203644-1.2.5.dist-info/entry_points.txt
topsis_akshat_102203644-1.2.5.dist-info/top_level.txt
topsis_akshat_102203644-1.2.5.dist-info/RECORD
