Metadata-Version: 2.4
Name: topsis_Akshat_102203644
Version: 1.2.5
Summary: A Python package to perform TOPSIS (Technique for Order Preference by Similarity to Ideal Solution).
Home-page: https://github.com/Akshatkhurana/TOPSIS-package
Author: Akshat Khurana
Author-email: akhurana_be22@thapar.edu
Classifier: Programming Language :: Python :: 3
Classifier: License :: OSI Approved :: MIT License
Classifier: Operating System :: OS Independent
Requires-Python: >=3.6
Requires-Dist: numpy
Requires-Dist: pandas
Dynamic: author
Dynamic: author-email
Dynamic: classifier
Dynamic: description
Dynamic: description-content-type
Dynamic: home-page
Dynamic: requires-dist
Dynamic: requires-python
Dynamic: summary
